{
    // "staticObjects": [{
    //     "id": 1,
    //     "imageName":"img-name",
    //     "position": {
    //         "pivot": 123,
    //         "width": 290,
    //         "top": 14,
    //         "height": 173,
    //         "left": 24
    //     },
    //     "orderinLayer":1,
    //     "inText": true,
    //     "label": "toad"}],
    // "animationObjects": [{
    //     "id": 0,
    //     "animName": "anim-name",
    //     "parent": "attached object",
    //     "loop": true,
    //     "draggable": false,
    //     "audio": {
    //         "audioName": "audio-name",
    //         "pngId": 1
    //     },
    //     "position": {
    //         "pivot": 123,
    //         "width": 290,
    //         "top": 14,
    //         "height": 173,
    //         "left": 24
    //     },
    //     "pngs": [{
    //         "id": 0,
    //         "fileName": "png-name-1"
    //     }, {
    //         "id": 1,
    //         "fileName": "png-name-2"
    //     }]

    // }],
     "Text": [{
            "id": 0,
            "text": "My eyes feel funny."
        }, {
            "id": 1,
            "text": "Why is that?"
        }],
    "storyImageFile": null,
    "audioFile": "scene19_child_stanza.mp3",
    "timestamps": [{
            "start": "235",
            "wordIdx": "0",
            "end": "595"
        },
        {
            "start": "685",
            "wordIdx": "1",
            "end": "1355"
        },
        {
            "start": "2025",
            "wordIdx": "2",
            "end": "2325"
        },
        {
            "start": "2325",
            "wordIdx": "3",
            "end": "3025"
        },
        {
            "start": "4055",
            "wordIdx": "4",
            "end": "4255"
        },
        {
            "start": "4290",
            "wordIdx": "5",
            "end": "4808"
        },
        {
            "start": "4915",
            "wordIdx": "6",
            "end": "5285"
        }
    ],

    "triggers": [{
        "args": {
            "stnzaId": 0,
            "textId": 0,
            "timestamp": null,
            "sceneObjectId": 0
        },
        "type": 0
    }, {
        "args": {
            "stnzaId": 0,
            "textId": 1,
            "timestamp": null,
            "sceneObjectId": 0
        },
        "type": 0
    }, {
        "args": {
            "stanzaId": 0,
            "textId": 2,
            "timestamp": null,
            "sceneObjectId": 0
        },
        "type": 0
    }, {
        "args": {
            "stanzaId": 1,
            "textId": 0,
            "timestamp": null,
            "sceneObjectId": 0
        },
        "type": 0
    }],
    "isTitle": false,
    "fontColor": "font-color",
    "textstartPosition": 120
}