<?xml version= "1.0" encoding="UTF-8"?>
<lipsync>
<phn msStart="5" msEnd="235" power="49">x</phn>
<word msStart="235" msEnd="615">I</word>
<phn msStart="235" msEnd="615" power="148">AY</phn>
<phn msStart="615" msEnd="665" power="47">x</phn>
<word msStart="665" msEnd="1085">am</word>
<phn msStart="665" msEnd="895" power="108">AE</phn>
<phn msStart="895" msEnd="1085" power="79">m</phn>
<phn msStart="1085" msEnd="1555" power="33">x</phn>
<word msStart="1555" msEnd="1795">an</word>
<phn msStart="1555" msEnd="1665" power="76">AH</phn>
<phn msStart="1665" msEnd="1795" power="67">n</phn>
<phn msStart="1795" msEnd="1965" power="40">x</phn>
<word msStart="1965" msEnd="2785">orange</word>
<phn msStart="1965" msEnd="2055" power="67">AO</phn>
<phn msStart="2055" msEnd="2085" power="65">r</phn>
<phn msStart="2085" msEnd="2315" power="107">AH</phn>
<phn msStart="2315" msEnd="2515" power="56">n</phn>
<phn msStart="2515" msEnd="2785" power="38">j</phn>
<phn msStart="2785" msEnd="2935" power="0">x</phn>
<word msStart="2935" msEnd="3825">duck</word>
<phn msStart="2935" msEnd="2985" power="69">d</phn>
<phn msStart="2985" msEnd="3335" power="74">AH</phn>
<phn msStart="3335" msEnd="3825" power="23">k</phn>
<phn msStart="3825" msEnd="3935" power="0">x</phn>
<phn msStart="3935" msEnd="4005" power="0">x</phn>
<phn msStart="4005" msEnd="4125" power="27">x</phn>
<word msStart="4125" msEnd="4335">Where</word>
<phn msStart="4125" msEnd="4205" power="69">w</phn>
<phn msStart="4205" msEnd="4305" power="74">EH</phn>
<phn msStart="4305" msEnd="4335" power="65">r</phn>
<word msStart="4335" msEnd="4665">can</word>
<phn msStart="4335" msEnd="4525" power="75">k</phn>
<phn msStart="4525" msEnd="4605" power="70">AE</phn>
<phn msStart="4605" msEnd="4665" power="95">n</phn>
<word msStart="4665" msEnd="4875">I</word>
<phn msStart="4665" msEnd="4875" power="102">AY</phn>
<phn msStart="4875" msEnd="4985" power="23">x</phn>
<word msStart="4985" msEnd="5685">play</word>
<phn msStart="4985" msEnd="5125" power="76">p</phn>
<phn msStart="5125" msEnd="5355" power="90">l</phn>
<phn msStart="5355" msEnd="5685" power="134">EY</phn>
<phn msStart="5685" msEnd="5885" power="0">x</phn>
</lipsync>
